vk_client/__about__.py
vk_client/__init__.py
vk_client/api.py
vk_client/captcha_handlers.py
vk_client/client.py
vk_client/config.py
vk_client/enums.py
vk_client/errors.py
vk_client/utils.py
vk_client/validators.py
vk_client/models/__init__.py
vk_client/models/_base.py
vk_client/models/_mixins.py
vk_client/models/bots_long_poll.py
vk_client/models/comment.py
vk_client/models/group.py
vk_client/models/group_event.py
vk_client/models/message.py
vk_client/models/photo.py
vk_client/models/post.py
vk_client/models/user.py
vk_client-0.2.0.dist-info/METADATA
vk_client-0.2.0.dist-info/RECORD
vk_client-0.2.0.dist-info/WHEEL
vk_client-0.2.0.dist-info/top_level.txt
